Workbook
Name valuevx: 42.314159

Sheet Rekap Invoice
A2: NO | B2: DATE | C2: INVOICE | D2: CUSTOMER ID | E2: DUE DATE | F2: NAME MR/MRS | G2: COMPANY NAME | H2: STREET ADRESS | I2: CITY | J2: PHONE | K2: DESCRIPTION | L2: QTY | M2: PRICE | N2: AMOUNT | O2: SUBTOTAL | P2: DISCOUNT | Q2: AFTER DISCOUNT | R2: PPN 11% | S2: PPh 2% | T2: OTHER | U2: TOTAL
A3: 1 | C3: INV/032/BSM/INVXI/2025 | D3: 001 | E3: 45968 | F3: Ibu April | G3: PT. Belirang Kalisari | H3: Jl Karanggayam I 2A Surabaya 60136 Indonesia | I3: Jawa Timur | J3: +62-812-7958-5758 | K3: Biaya Ocean freight + Dooring PT. Indah Kiat Perawang 14 x 20GP all in | L3: 14 | M3: 14650000 | N3: =L3*M3 -> 205100000 | O3: =N3 -> 205100000 | R3: =Q3*11/100 -> 0 | S3: =Q3*2/100 -> 0 | T3: 0 | U3: =Q3+R3-S3 -> 0
A4: =+A3+1 -> 2 | C4: INV/033/BSM/INVXI/2025 | D4: 002 | E4: 45968 | F4: Pak Yoseph Krisna | G4: PT. Tangguh Birawa Persada | H4: Jl Pulo Mas VIII No 11 Kayu Putih , Pulo Gadung | I4: Jakarta Timur | J4: +62-812-8039-8690 | K4: Biaya Ocean freight + Dooring Bangkinang 8 x 20GP all in | L4: 8 | M4: 17500000 | N4: =L4*M4 -> 140000000 | O4: =N4 -> 140000000 | P4: 0 | Q4: 0 | R4: =Q4*11/100 -> 0 | S4: =Q4*2/100 -> 0 | T4: 0 | U4: =Q4+R4-S4 -> 0
A5: =+A4+1 -> 3 | C5: INV/034/BSM/INVXII/2025 | D5: 003 | E5: 45968 | F5: Pak Yoseph Krisna | G5: PT. Tangguh Birawa Persada | H5: Jl Pulo Mas VIII No 11 Kayu Putih , Pulo Gadung | I5: Jakarta Timur | J5: +62-812-8039-8690 | K5: Biaya Ocean freight + Dooring Bangka 26 x 20GP all in | L5: 26 | M5: 13500000 | N5: =L5*M5 -> 351000000 | O5: =N5 -> 351000000 | P5: 0 | Q5: 0 | R5: =Q5*11/100 -> 0 | S5: =Q5*2/100 -> 0 | T5: 0 | U5: =Q5+R5-S5 -> 0
A6: =+A5+1 -> 4 | C6: INV/035/BSM/INVXI/2025 | D6: 004 | E6: 45972 | F6: Ibu April | G6: PT. Belirang Kalisari | H6: Jl Karanggayam I 2A Surabaya 60136 Indonesia | I6: Jawa Timur | J6: +62-812-7958-5758 | K6: Biaya Ocean freight + Dooring PT. Indah Kiat Perawang 7 x 20GP all in | L6: 7 | M6: 14650000 | N6: =L6*M6 -> 102550000 | O6: =N6 -> 102550000 | P6: 0 | Q6: 0 | R6: =Q6*11/100 -> 0 | S6: =Q6*2/100 -> 0 | T6: 0 | U6: =Q6+R6-S6 -> 0
A7: =+A6+1 -> 5 | C7: INV/036/BSM/INVXII/2025 | D7: 005 | E7: 45970 | F7: Pak Yoseph Krisna | G7: PT. Tangguh Birawa Persada | H7: Jl Pulo Mas VIII No 11 Kayu Putih , Pulo Gadung | I7: Jakarta Timur | J7: +62-812-8039-8690 | K7: Biaya Storage dan Demurage dari Tgl 18 Nov 2025 sd 10 Dec 2025 | L7: 2 | M7: 14800000 | N7: =L7*M7 -> 29600000 | O7: =N7 -> 29600000 | P7: 0 | Q7: 0 | R7: =Q7*11/100 -> 0 | S7: =Q7*2/100 -> 0 | T7: 0 | U7: =Q7+R7-S7 -> 0
A8: =+A7+1 -> 6 | C8: INV/037/BSM/INVXII/2025 | D8: 006 | E8: 45970 | F8: Pak Yoseph Krisna | G8: PT. Tangguh Birawa Persada | H8: Jl Pulo Mas VIII No 11 Kayu Putih , Pulo Gadung | I8: Jakarta Timur | J8: +62-812-8039-8690 | K8: Biaya Storage dan Demurage dari Tgl 18 Nov 2025 sd 22 Dec 2025 | L8: 4 | M8: 10895880 | N8: 10895880 | O8: =N8 -> 10895880 | P8: 0 | Q8: 0 | R8: =Q8*11/100 -> 0 | S8: =Q8*2/100 -> 0 | T8: 0 | U8: =Q8+R8-S8 -> 0
A9: =+A8+1 -> 7 | C9: INV/038/BSM/INVXII/2025 | D9: 007 | E9: 45983 | F9: Pak Yoseph Krisna | G9: PT. Tangguh Birawa Persada / QQ PT. Putra Putri Karya | H9: Jl Pulo Mas VIII No 11 Kayu Putih , Pulo Gadung | I9: Jakarta Timur | J9: +62-812-8039-8690 | K9: Biaya Ocean freight + Dooring Bangka 7 x 20GP all in | L9: 7 | M9: 13500000 | N9: =L9*M9 -> 94500000 | O9: =N9 -> 94500000 | P9: 0 | Q9: 0 | R9: =Q9*11/100 -> 0 | S9: =Q9*2/100 -> 0 | T9: 0 | U9: =Q9+R9-S9 -> 0
A10: 8 | C10: INV/039/BSM/INVXII/2025 | D10: 008 | E10: 46020 | F10: Ibu April | G10: PT. Belirang Kalisari | H10: Jl Karanggayam I 2A Surabaya 60136 Indonesia | I10: Jawa Timur | J10: +62-812-7958-5758 | K10: Biaya Ocean freight + Dooring PT. Indah Kiat Perawang 16 x 20GP all in | L10: 16 | M10: 14650000 | N10: =L10*M10 -> 234400000 | O10: =N10 -> 234400000 | P10: 0 | Q10: 0 | R10: =Q10*11/100 -> 0 | S10: =Q10*2/100 -> 0 | T10: 0 | U10: =Q10+R10-S10 -> 0
A11: 9 | C11: INV/040/BSM/INVI/2026 | D11: 009 | E11: 46028 | F11: Pak Yoseph Krisna | G11: PT. Tangguh Birawa Persada | H11: Jl Pulo Mas VIII No 11 Kayu Putih , Pulo Gadung | I11: Jakarta Timur | J11: +62-812-8039-8690 | K11: Biaya Ocean freight + Dooring Bangka 8 x 20GP all in | L11: 8 | M11: 13500000 | N11: =L11*M11 -> 108000000 | O11: =N11 -> 108000000 | P11: 0 | Q11: 0 | R11: =Q11*11/100 -> 0 | S11: =Q11*2/100 -> 0 | T11: 0 | U11: =Q11+R11-S11 -> 0
A12: 10 | C12: INV/041/BSM/INVI/2026 | D12: 010 | E12: 46045 | F12: Pak Yoseph Krisna | G12: PT. Tangguh Birawa Persada | H12: Jl Pulo Mas VIII No 11 Kayu Putih , Pulo Gadung | I12: Jakarta Timur | J12: +62-812-8039-8690 | K12: Biaya Storage Demurage 2 x 20GP Perawang - Bangkinang | L12: 2 | M12: 17500000 | N12: =L12*M12 -> 35000000 | O12: =N12 -> 35000000 | P12: 0 | Q12: 0 | R12: =Q12*11/100 -> 0 | S12: =Q12*2/100 -> 0 | T12: 0 | U12: =Q12+R12-S12 -> 0
A13: 11 | C13: INV/042/BSM/INVII/2026 | D13: 011 | E13: 46055 | F13: Pak Yoseph Krisna | G13: PT. Tangguh Birawa Persada | H13: Jl Pulo Mas VIII No 11 Kayu Putih , Pulo Gadung | I13: Jakarta Timur | J13: +62-812-8039-8690 | K13: Biaya Ocean freight + Dooring Bangkinang 8 x 20GP all in | L13: 8 | M13: 17500000 | N13: =L13*M13 -> 140000000 | O13: =N13 -> 140000000 | P13: 0 | Q13: 0 | R13: =Q13*11/100 -> 0 | S13: =Q13*2/100 -> 0 | T13: 0 | U13: =Q13+R13-S13 -> 0
A14: 12 | C14: INV/043/BSM/INVII/2026 | D14: 012 | E14: 46059 | F14: Ibu April | G14: PT. Belirang Kalisari | H14: Jl Karanggayam I 2A Surabaya 60136 Indonesia | I14: Jawa Timur | J14: +62-812-7958-5758 | K14: Biaya Ocean freight + Dooring PT. Indah Kiat OKI 2 x 20GP all in | L14: 2 | M14: 16886000 | N14: =L14*M14 -> 33772000 | O14: =N14 -> 33772000 | P14: 0 | Q14: 0 | R14: =Q14*11/100 -> 0 | S14: =Q14*2/100 -> 0 | T14: 0 | U14: =Q14+R14-S14 -> 0
A15: 13 | C15: INV/044/BSM/INVII/2026 | D15: 013 | E15: 46072 | F15: Ibu April | G15: PT. Belirang Kalisari | H15: Jl Karanggayam I 2A Surabaya 60136 Indonesia | I15: Jawa Timur | J15: +62-812-7958-5758 | K15: Biaya Ocean freight + Dooring PT. Indah Kiat Perawang 15 x 20GP all in | L15: 15 | M15: 14860000 | N15: =L15*M15 -> 222900000 | O15: =N15 -> 222900000 | P15: 0 | Q15: 0 | R15: =Q15*11/100 -> 0 | S15: =Q15*2/100 -> 0 | T15: 0 | U15: =Q15+R15-S15 -> 0
A16: 14 | C16: INV/045/BSM/INVII/2026 | D16: 014 | E16: 46072 | F16: Ibu April | G16: PT. Belirang Kalisari | H16: Jl Karanggayam I 2A Surabaya 60136 Indonesia | I16: Jawa Timur | J16: +62-812-7958-5758 | K16: Biaya Ocean freight + Dooring PT. Indah Kiat OKI 4 x 20GP all in | L16: 4 | M16: 16886000 | N16: =L16*M16 -> 67544000 | O16: =N16 -> 67544000 | P16: 0 | Q16: 0 | R16: =Q16*11/100 -> 0 | S16: =Q16*2/100 -> 0 | T16: 0 | U16: =Q16+R16-S16 -> 0
A17: 15 | C17: INV/047/BSM/INVIII/2026 | D17: 015 | E17: 46097 | F17: Ibu April | G17: PT. Belirang Kalisari | H17: Jl Karanggayam I 2A Surabaya 60136 Indonesia | I17: Jawa Timur | J17: +62-812-7958-5758 | K17: Biaya Ocean freight + Dooring PT. Indah Kiat PRW 10 x 20GP all in | L17: 10 | M17: 14860000 | N17: =L17*M17 -> 148600000 | O17: =N17 -> 148600000 | P17: 0 | Q17: 0 | R17: =Q17*11/100 -> 0 | S17: =Q17*2/100 -> 0 | T17: 0 | U17: =Q17+R17-S17 -> 0
A18: 16 | C18: INV/048/BSM/INVIII/2026 | D18: 016 | E18: 46112 | F18: Ibu April | G18: PT. Belirang Kalisari | H18: Jl Karanggayam I 2A Surabaya 60136 Indonesia | I18: Jawa Timur | J18: +62-812-7958-5758 | K18: Biaya Ocean freight Cy - Fio PT. Indah Kiat PRW 6 x 20GP all in | L18: 6 | M18: 15250000 | N18: =L18*M18 -> 91500000 | O18: =N18 -> 91500000 | P18: 0 | Q18: =O18*P18 -> 0 | R18: =P18*Q18 -> 0 | S18: =Q18*R18 -> 0 | T18: 0 | U18: =S18*T18 -> 0
A19: 17 | C19: INV/049/BSM/INVIV/2026 | D19: 017 | E19: 46122 | F19: Ibu April | G19: PT. Belirang Kalisari | H19: Jl Karanggayam I 2A Surabaya 60136 Indonesia | I19: Jawa Timur | J19: +62-812-7958-5758 | K19: Biaya Ocean freight Cy - Fio PT. Indah Kiat PRW 9 x 20GP all in | L19: 9 | M19: 16250000 | N19: =L19*M19 -> 146250000 | O19: =N19 -> 146250000 | P19: 0 | Q19: 0 | R19: =Q19*11/100 -> 0 | S19: =Q19*2/100 -> 0 | T19: 0 | U19: =Q19+R19-S19 -> 0
A20: 18 | C20: INV/050/BSM/INVV/2026 | D20: 018 | E20: 46150 | F20: Ibu April | G20: PT. Belirang Kalisari | H20: Jl Karanggayam I 2A Surabaya 60136 Indonesia | I20: Jawa Timur | J20: +62-812-7958-5758 | K20: Biaya Ocean freight Cy - Fio PT. Indah Kiat OKI 4 x 20GP all in | L20: 4 | M20: 17886000 | N20: =L20*M20 -> 71544000 | O20: =N20 -> 71544000 | P20: 0 | Q20: 0 | R20: =Q20*11/100 -> 0 | S20: =Q20*2/100 -> 0 | T20: 0 | U20: =Q20+R20-S20 -> 0
A21: 19 | C21: INV/051/BSM/INVV/2026 | D21: 019 | E21: 46162 | F21: Ibu April | G21: PT. Belirang Kalisari | H21: Jl Karanggayam I 2A Surabaya 60136 Indonesia | I21: Jawa Timur | J21: +62-812-7958-5758 | K21: Biaya Ocean freight Cy - Fio PT. Indah Kiat PRW 8 x 20GP all in | L21: 8 | M21: 16250000 | N21: =L21*M21 -> 130000000 | O21: =N21 -> 130000000 | P21: 0 | Q21: 0 | R21: =Q21*11/100 -> 0 | S21: =Q21*2/100 -> 0 | T21: 0 | U21: =Q21+R21-S21 -> 0
A22: 20 | C22: INV/052/BSM/INVVI/2026 | D22: 020 | E22: 46195 | F22: Bpk Zuher | G22: PT. Tangguh Birawa Persada | H22: Jl Pulo Mas VIII No 11 Kayu Putih , Pulo Gadung | I22: Jakarta Timur | J22: +62-812-8039-8690 | K22: Biaya Trucking Pekan Baru - Bangkinang 2 x 20GP | L22: 2 | M22: 5300000 | N22: =L22*M22 -> 10600000 | O22: =N22 -> 10600000 | P22: 0 | Q22: 0 | R22: =Q22*11/100 -> 0 | S22: =Q22*2/100 -> 0 | T22: 0 | U22: =Q22+R22-S22 -> 0
A23: 21 | C23: INV/053/BSM/INVVII/2026 | D23: 021 | E23: 46210 | F23: Ibu April | G23: PT. Belirang Kalisari | H23: Jl Karanggayam I 2A Surabaya 60136 Indonesia | I23: Jawa Timur | J23: +62-812-7958-5758 | K23: Biaya Ocean freight Door - Fio PT. Indah Kiat OKI 4 x 20GP all in | L23: 4 | M23: 18000000 | N23: =L23*M23 -> 72000000 | O23: =N23 -> 72000000 | P23: 0 | Q23: 0 | R23: =Q23*11/100 -> 0 | S23: =Q23*2/100 -> 0 | T23: 0 | U23: =Q23+R23-S23 -> 0
A24: 22 | C24: INV/054/BSM/INVVII/2025 | D24: 022 | E24: 46219 | F24: Ibu April | G24: PT. Belirang Kalisari | H24: Jl Karanggayam I 2A Surabaya 60136 Indonesia | I24: Jawa Timur | J24: +62-812-7958-5758 | K24: Biaya Ocean freight Door - Fio PT. Indah Kiat PRW 5 x 20GP all in | L24: 5 | M24: 16250000 | N24: =L24*M24 -> 81250000 | O24: =N24 -> 81250000 | P24: 0 | Q24: 0 | R24: =Q24*11/100 -> 0 | S24: =Q24*2/100 -> 0 | T24: 0 | U24: =Q24+R24-S24 -> 0
A25: 23 | C25: INV/055/BSM/INVXII/2025 | D25: 023 | E25: 45983 | F25: Isi Nama Customer | G25: Isi Nama Perusahaan | H25: Isi Alamat | I25: Isi Kota | J25: Isi Nomor Telepon | K25: Isi Deskripsi | L25: 0 | M25: 0 | N25: =L25*M25 -> 0 | O25: =N25 -> 0 | P25: 0 | Q25: 0 | R25: =Q25*11/100 -> 0 | S25: =Q25*2/100 -> 0 | T25: 0 | U25: =Q25+R25-S25 -> 0
A26: 24 | C26: INV/056/BSM/INVXII/2025 | D26: 024 | E26: 45983 | F26: Isi Nama Customer | G26: Isi Nama Perusahaan | H26: Isi Alamat | I26: Isi Kota | J26: Isi Nomor Telepon | K26: Isi Deskripsi | L26: 0 | M26: 0 | N26: =L26*M26 -> 0 | O26: =N26 -> 0 | P26: 0 | Q26: 0 | R26: =Q26*11/100 -> 0 | S26: =Q26*2/100 -> 0 | T26: 0 | U26: =Q26+R26-S26 -> 0
A27: 25 | C27: INV/057/BSM/INVXII/2025 | D27: 025 | E27: 45983 | F27: Isi Nama Customer | G27: Isi Nama Perusahaan | H27: Isi Alamat | I27: Isi Kota | J27: Isi Nomor Telepon | K27: Isi Deskripsi | L27: 0 | M27: 0 | N27: =L27*M27 -> 0 | O27: =N27 -> 0 | P27: 0 | Q27: 0 | R27: =Q27*11/100 -> 0 | S27: =Q27*2/100 -> 0 | T27: 0 | U27: =Q27+R27-S27 -> 0
A28: 26 | C28: INV/058/BSM/INVXII/2025 | D28: 026 | E28: 45983 | F28: Isi Nama Customer | G28: Isi Nama Perusahaan | H28: Isi Alamat | I28: Isi Kota | J28: Isi Nomor Telepon | K28: Isi Deskripsi | L28: 0 | M28: 0 | N28: =L28*M28 -> 0 | O28: =N28 -> 0 | P28: 0 | Q28: 0 | R28: =Q28*11/100 -> 0 | S28: =Q28*2/100 -> 0 | T28: 0 | U28: =Q28+R28-S28 -> 0
A29: 27 | C29: INV/059/BSM/INVXII/2025 | D29: 027 | E29: 45983 | F29: Isi Nama Customer | G29: Isi Nama Perusahaan | H29: Isi Alamat | I29: Isi Kota | J29: Isi Nomor Telepon | K29: Isi Deskripsi | L29: 0 | M29: 0 | N29: =L29*M29 -> 0 | O29: =N29 -> 0 | P29: 0 | Q29: 0 | R29: =Q29*11/100 -> 0 | S29: =Q29*2/100 -> 0 | T29: 0 | U29: =Q29+R29-S29 -> 0
A30: 28 | C30: INV/060/BSM/INVXII/2025 | D30: 028 | E30: 45983 | F30: Isi Nama Customer | G30: Isi Nama Perusahaan | H30: Isi Alamat | I30: Isi Kota | J30: Isi Nomor Telepon | K30: Isi Deskripsi | L30: 0 | M30: 0 | N30: =L30*M30 -> 0 | O30: =N30 -> 0 | P30: 0 | Q30: 0 | R30: =Q30*11/100 -> 0 | S30: =Q30*2/100 -> 0 | T30: 0 | U30: =Q30+R30-S30 -> 0
... A52: 50 | C52: INV/081/BSM/INVXII/2025 | D52: 050 | E52: 45983 | F52: Isi Nama Customer | G52: Isi Nama Perusahaan | H52: Isi Alamat | I52: Isi Kota | J52: Isi Nomor Telepon | K52: Isi Deskripsi | L52: 0 | M52: 0 | N52: =L52*M52 -> 0 | O52: =N52 -> 0 | P52: 0 | Q52: 0 | R52: =Q52*11/100 -> 0 | S52: =Q52*2/100 -> 0 | T52: 0 | U52: =Q52+R52-S52 -> 0

Sheet Invoice 001
A1: INVOICE
A2: PT. BHUMI SELARAS MITRA
A3: Menteng Square Office Tower A Lt 2 Unit AK 8, Kel. Kenari, Kec. Senen | F3: DATE | G3: =VLOOKUP(G4,'Rekap Invoice'!$C$3:$E$52,3,FALSE) -> 46219
A4: Kota Adm. Jakarta Pusat, Provinsi DKI Jakarta 10430 | F4: INVOICE NO | G4: INV/054/BSM/INVVII/2025
A5: Phone: +62-811-8627-047 l Email : pt.bhumiselarasmitra@gmail.com | F5: CUSTOMER ID | G5: =VLOOKUP(G4,'Rekap Invoice'!$C$3:$D$52,2,FALSE) -> 022
F6: DUE DATE | G6: =VLOOKUP(G4,'Rekap Invoice'!$C$3:$E$52,3,FALSE) -> 46219
A9: BILL TO
A11: Name Mr/Mrs. | B11: : | C11: =VLOOKUP(G4,'Rekap Invoice'!$C$3:$F$52,4,FALSE) -> Ibu April
A12: Company Name | B12: : | C12: =VLOOKUP(G4,'Rekap Invoice'!$C$3:$G$52,5,FALSE) -> PT. Belirang Kalisari
A13: Street Address | B13: : | C13: =VLOOKUP(G4,'Rekap Invoice'!$C$3:$H$52,6,FALSE) -> Jl Karanggayam I 2A Surabaya 60136 Indonesia
A14: City | B14: : | C14: =VLOOKUP(G4,'Rekap Invoice'!$C$3:$I$54,7,FALSE) -> Jawa Timur
A15: Phone | B15: : | C15: =VLOOKUP(G4,'Rekap Invoice'!$C$3:$J$53,8,FALSE) -> +62-812-7958-5758
A17: DESCRIPTION | E17: QTY | F17: PRICE | G17: AMOUNT
A18: =VLOOKUP(G4,'Rekap Invoice'!$C$3:$R$53,9,FALSE) -> Biaya Ocean freight Door - Fio PT. Indah Kiat PRW 5 x 20GP all in | E18: =VLOOKUP(G4,'Rekap Invoice'!$C$3:$U$55,10,FALSE) -> 5 | F18: =VLOOKUP(G4,'Rekap Invoice'!$C$3:$V$53,11,FALSE) -> 16250000 | G18: =VLOOKUP(G4,'Rekap Invoice'!$C$3:$U$53,12,FALSE) -> 81250000
G19: =E19*F19 -> 0
G20: =E20*F20 -> 0
G21: =E21*F21 -> 0
G22: =E22*F22 -> 0
G23: =E23*F23 -> 0
G24: =E24*F24 -> 0
G25: =E25*F25 -> 0
G26: =E26*F26 -> 0
G27: =E27*F27 -> 0
G28: =E28*F28 -> 0
G29: =E29*F29 -> 0
G30: =E30*F30 -> 0
... G33: =E33*F33 -> 0
D34: [42] | E34: Subtotal | G34: =VLOOKUP(G4,'Rekap Invoice'!$C$3:$U$53,13,FALSE) -> 81250000
E35: Discount | G35: =VLOOKUP(G4,'Rekap Invoice'!$C$3:$P$52,14,FALSE) -> 0
A36: ATTENTION | E36: After Discount | G36: =VLOOKUP(G4,'Rekap Invoice'!$C$3:$Q$52,15,FALSE) -> 0
A37: 1. Items that have been purchased cannot be returned. | E37: PPN 11% | G37: =VLOOKUP(G4,'Rekap Invoice'!$C$3:$S$53,16,FALSE) -> 0
A38: 2. Payment Information : | E38: PPh 2% | G38: =VLOOKUP(G4,'Rekap Invoice'!$C$3:$U$52,17,FALSE) -> 0
A39: Bank Code : 014 | E39: Other | G39: =VLOOKUP(G4,'Rekap Invoice'!$C$3:$T$52,18,FALSE) -> 0
A40: Bank Name : BCA KCU Kramat Jaya | E40: TOTAL | G40: =VLOOKUP(G4,'Rekap Invoice'!$C$3:$U$52,19,FALSE) -> 0
A41: Name Account : BHUMI SELARAS MITRA | E41: Make all checks payable to
A42: Rek Number : 414-2485-676 | E42: PT. Bhumi Selaras Mitra
A50: ( Ari Wahyudi )

Sheet Customer ID
B2: CUSTOMER ID | C2: CUSTOMER NAME
B3: 001 | C3: PT. Belirang Kalisari
B4: 002 | C4: PT. Tangguh Birawa Persada
B5: 003 | C5: PT. Inti Jaya Elektronik
B6: 004 | C6: PT. Toko Baru Avo
B7: 005 | C7: PT. Ones Law Group
